pytglue.py
pytglue-1.0.2.dist-info/LICENSE
pytglue-1.0.2.dist-info/METADATA
pytglue-1.0.2.dist-info/WHEEL
pytglue-1.0.2.dist-info/top_level.txt
pytglue-1.0.2.dist-info/RECORD
