Metadata-Version: 2.1
Name: pytglue
Version: 1.0.2
Summary: An Unofficial Python Wrapper for ITGlue.
Home-page: UNKNOWN
License: UNKNOWN
Platform: UNKNOWN
Classifier: Programming Language :: Python :: 3
Classifier: Programming Language :: Python :: 3.6
Classifier: Programming Language :: Python :: 3.7
Classifier: Operating System :: OS Independent
